omc_ssh/__init__.py
omc_ssh/config/__init__.py
omc_ssh/config/settings.yaml
omc_ssh/service/__init__.py
omc_ssh/service/ssh_service.py
omc_ssh/ssh/__init__.py
omc_ssh/ssh/ssh.py
omc_ssh-0.0.6.dist-info/METADATA
omc_ssh-0.0.6.dist-info/WHEEL
omc_ssh-0.0.6.dist-info/top_level.txt
omc_ssh-0.0.6.dist-info/RECORD
