Metadata-Version: 2.1
Name: omc-ssh
Version: 0.0.6
Summary: ssh plugin for omc
Home-page: https://github.com/linewx/omc-ssh
Author: Lu Ganlin
Author-email: linewx1981@gmail.com
License: MIT
Platform: UNKNOWN
Requires-Dist: omc (>=0.2.3)
